jgtagentic/__init__.py
jgtagentic/agentic_decider.py
jgtagentic/agentic_entry_orchestrator.py
jgtagentic/batch_fdbscan.py
jgtagentic/campaign_env.py
jgtagentic/dashboard.py
jgtagentic/enhanced_fdb_scanner.py
jgtagentic/entry_script_gen.py
jgtagentic/fdbloopscan.py
jgtagentic/fdbscan_agent.py
jgtagentic/intent_spec.py
jgtagentic/jgtagenticcli.py
jgtagentic/jupyter_book_agent.py
jgtagentic/observation_capture.py
jgtagentic-0.0.12.dist-info/METADATA
jgtagentic-0.0.12.dist-info/WHEEL
jgtagentic-0.0.12.dist-info/entry_points.txt
jgtagentic-0.0.12.dist-info/top_level.txt
jgtagentic-0.0.12.dist-info/RECORD
